{"mean":{"confidence_interval":{"confidence_level":0.95,"lower_bound":952747.5361680208,"upper_bound":962935.429167186},"point_estimate":957552.0157418085,"standard_error":2601.4111340113027},"median":{"confidence_interval":{"confidence_level":0.95,"lower_bound":943642.8975155279,"upper_bound":951329.5549999999},"point_estimate":946017.4663461538,"standard_error":2254.633434006086},"median_abs_dev":{"confidence_interval":{"confidence_level":0.95,"lower_bound":7150.499684755277,"upper_bound":16716.69843498398},"point_estimate":10701.462333169673,"standard_error":2493.5294920675237},"slope":{"confidence_interval":{"confidence_level":0.95,"lower_bound":952432.4796280257,"upper_bound":962742.0646934847},"point_estimate":957241.7010758091,"standard_error":2633.6034343421084},"std_dev":{"confidence_interval":{"confidence_level":0.95,"lower_bound":18626.413351905514,"upper_bound":32840.43116747693},"point_estimate":26033.634262384818,"standard_error":3638.25701276538}}